LICENSE
MANIFEST.in
README.rst
VERSION
requirements.txt
setup.py
src/flask_openldap/__init__.py
src/flask_openldap/manager.py
src/flask_openldap/user.py
src/flask_openldap/utils.py
src/flask_openldap.egg-info/PKG-INFO
src/flask_openldap.egg-info/SOURCES.txt
src/flask_openldap.egg-info/dependency_links.txt
src/flask_openldap.egg-info/requires.txt
src/flask_openldap.egg-info/top_level.txt
src/flask_openldap.egg-info/zip-safe
src/flask_openldap/tests/__init__.py