Metadata-Version: 2.1
Name: flask-openldap
Version: 0.2.0
Summary: Flask extension to query an openLDAP server
Home-page: https://github.com/cdumay/flask-openldap
Author: Cedric DUMAY
Author-email: cedric.dumay@gmail.com
License: Apache License
Platform: UNKNOWN
Classifier: Programming Language :: Python
License-File: LICENSE
